add.py
binarymans_mypackage_iknabil-0.1.0.dist-info/METADATA
binarymans_mypackage_iknabil-0.1.0.dist-info/WHEEL
binarymans_mypackage_iknabil-0.1.0.dist-info/top_level.txt
binarymans_mypackage_iknabil-0.1.0.dist-info/RECORD
