Metadata-Version: 2.4
Name: binarymans_mypackage_iknabil
Version: 0.1.0
Summary: A simple package to add two numbers
Author-email: Ibrahim Khalil Nabil <ibrahimkhalilnabil321@gmail.com>
License-Expression: MIT
Project-URL: Homepage, https://github.com/yourusername/addtwo
Requires-Python: >=3.7
